<?xml version = '1.0' encoding = 'UTF-8'?>
<TableSettings class="oracle.dbtools.raptor.controls.grid.RaptorGridPersistedSettings" xmlns="http://xmlns.oracle.com/jdeveloper/110000/Table-attributes">
   <columnPositions class="java.util.ArrayList">
      <Item class="java.lang.String">DISTRIBUTION_ID</Item>
      <Item class="java.lang.String">BOOK_TYPE_CODE</Item>
      <Item class="java.lang.String">ASSET_ID</Item>
      <Item class="java.lang.String">UNITS_ASSIGNED</Item>
      <Item class="java.lang.String">DATE_EFFECTIVE</Item>
      <Item class="java.lang.String">CODE_COMBINATION_ID</Item>
      <Item class="java.lang.String">LOCATION_ID</Item>
      <Item class="java.lang.String">TRANSACTION_HEADER_ID_IN</Item>
      <Item class="java.lang.String">LAST_UPDATE_DATE</Item>
      <Item class="java.lang.String">LAST_UPDATED_BY</Item>
      <Item class="java.lang.String">DATE_INEFFECTIVE</Item>
      <Item class="java.lang.String">ASSIGNED_TO</Item>
      <Item class="java.lang.String">TRANSACTION_HEADER_ID_OUT</Item>
      <Item class="java.lang.String">TRANSACTION_UNITS</Item>
      <Item class="java.lang.String">RETIREMENT_ID</Item>
      <Item class="java.lang.String">LAST_UPDATE_LOGIN</Item>
      <Item class="java.lang.String">CAPITAL_ADJ_ACCOUNT_CCID</Item>
      <Item class="java.lang.String">GENERAL_FUND_ACCOUNT_CCID</Item>
   </columnPositions>
   <columnWidths>
      <Item>108</Item>
      <Item>111</Item>
      <Item>67</Item>
      <Item>105</Item>
      <Item>145</Item>
      <Item>142</Item>
      <Item>88</Item>
      <Item>171</Item>
      <Item>145</Item>
      <Item>113</Item>
      <Item>145</Item>
      <Item>89</Item>
      <Item>181</Item>
      <Item>127</Item>
      <Item>99</Item>
      <Item>125</Item>
      <Item>172</Item>
      <Item>183</Item>
   </columnWidths>
   <searchParams class="java.util.ArrayList"/>
   <sortClauses>
      <Item/>
   </sortClauses>
   <uniqueName>IdeConnections%23OFPI-P3-TNSSELECT    *
FROM      fa_distribution_history fdh
WHERE     1 = 1
and   asset_id = 18342</uniqueName>
</TableSettings>
