<?xml version = '1.0' encoding = 'UTF-8'?>
<TableSettings class="oracle.dbtools.raptor.controls.grid.RaptorGridPersistedSettings" xmlns="http://xmlns.oracle.com/jdeveloper/110000/Table-attributes">
   <columnPositions class="java.util.ArrayList">
      <Item class="java.lang.String">USERNAME</Item>
      <Item class="java.lang.String">USER_ID</Item>
      <Item class="java.lang.String">PASSWORD</Item>
      <Item class="java.lang.String">ACCOUNT_STATUS</Item>
      <Item class="java.lang.String">LOCK_DATE</Item>
      <Item class="java.lang.String">EXPIRY_DATE</Item>
      <Item class="java.lang.String">DEFAULT_TABLESPACE</Item>
      <Item class="java.lang.String">TEMPORARY_TABLESPACE</Item>
      <Item class="java.lang.String">LOCAL_TEMP_TABLESPACE</Item>
      <Item class="java.lang.String">CREATED</Item>
      <Item class="java.lang.String">PROFILE</Item>
      <Item class="java.lang.String">INITIAL_RSRC_CONSUMER_GROUP</Item>
      <Item class="java.lang.String">EXTERNAL_NAME</Item>
      <Item class="java.lang.String">PASSWORD_VERSIONS</Item>
      <Item class="java.lang.String">EDITIONS_ENABLED</Item>
      <Item class="java.lang.String">AUTHENTICATION_TYPE</Item>
      <Item class="java.lang.String">PROXY_ONLY_CONNECT</Item>
      <Item class="java.lang.String">COMMON</Item>
      <Item class="java.lang.String">LAST_LOGIN</Item>
      <Item class="java.lang.String">ORACLE_MAINTAINED</Item>
      <Item class="java.lang.String">INHERITED</Item>
      <Item class="java.lang.String">DEFAULT_COLLATION</Item>
      <Item class="java.lang.String">IMPLICIT</Item>
      <Item class="java.lang.String">ALL_SHARD</Item>
   </columnPositions>
   <columnWidths>
      <Item>173</Item>
      <Item>62</Item>
      <Item>76</Item>
      <Item>117</Item>
      <Item>138</Item>
      <Item>138</Item>
      <Item>131</Item>
      <Item>148</Item>
      <Item>151</Item>
      <Item>138</Item>
      <Item>61</Item>
      <Item>192</Item>
      <Item>103</Item>
      <Item>132</Item>
      <Item>117</Item>
      <Item>138</Item>
      <Item>138</Item>
      <Item>65</Item>
      <Item>341</Item>
      <Item>128</Item>
      <Item>73</Item>
      <Item>126</Item>
      <Item>63</Item>
      <Item>76</Item>
   </columnWidths>
   <searchParams class="java.util.ArrayList"/>
   <sortClauses>
      <Item class="java.lang.String">2 asc</Item>
      <Item/>
   </sortClauses>
   <uniqueName>IdeConnections%23HUB-PRODselect *
from dba_users
where 1=1
--and username like '2125%'
order by 1</uniqueName>
</TableSettings>
